{"mean":{"confidence_interval":{"confidence_level":0.95,"lower_bound":7535736753.0,"upper_bound":7584615863.0425005},"point_estimate":7561517573.9,"standard_error":12477013.905000828},"median":{"confidence_interval":{"confidence_level":0.95,"lower_bound":7536609105.0,"upper_bound":7591321081.5},"point_estimate":7568855419.0,"standard_error":12841338.532080693},"median_abs_dev":{"confidence_interval":{"confidence_level":0.95,"lower_bound":6200639.322316647,"upper_bound":67826267.51374304},"point_estimate":32374367.336440086,"standard_error":18124602.13641927},"slope":null,"std_dev":{"confidence_interval":{"confidence_level":0.95,"lower_bound":19725944.32595765,"upper_bound":54210405.6071048},"point_estimate":41616370.762045406,"standard_error":8874374.180326654}}