{"mean":{"confidence_interval":{"confidence_level":0.95,"lower_bound":1928155.1,"upper_bound":2593056.6550000003},"point_estimate":2249092.3666666667,"standard_error":171435.4556387972},"median":{"confidence_interval":{"confidence_level":0.95,"lower_bound":1855937.0,"upper_bound":2686879.666666667},"point_estimate":2149543.833333333,"standard_error":195316.1450301285},"median_abs_dev":{"confidence_interval":{"confidence_level":0.95,"lower_bound":68813.88937830913,"upper_bound":1030953.813996911},"point_estimate":557537.6505017276,"standard_error":251668.22560216175},"slope":null,"std_dev":{"confidence_interval":{"confidence_level":0.95,"lower_bound":290186.0149615282,"upper_bound":729349.5772983847},"point_estimate":573882.8078431708,"standard_error":108865.73039364317}}